ONEcityAPI/ONEcityAPI.py
ONEcityAPI/__init__.py
ONEcityAPI/consumption.py
ONEcityAPI/consumptions.py
ONEcityAPI/customer.py
ONEcityAPI/exceptions.py
ONEcityAPI/token.py
ONEcityAPI/user.py
ONEcityAPI-0.0.1.dist-info/LICENSE
ONEcityAPI-0.0.1.dist-info/METADATA
ONEcityAPI-0.0.1.dist-info/WHEEL
ONEcityAPI-0.0.1.dist-info/top_level.txt
ONEcityAPI-0.0.1.dist-info/RECORD
